pytility/__init__.py
pytility/__version__.py
pytility/files.py
pytility/iterables.py
pytility/parsers.py
pytility/strings.py
pytility-0.3.0.dist-info/LICENSE
pytility-0.3.0.dist-info/METADATA
pytility-0.3.0.dist-info/WHEEL
pytility-0.3.0.dist-info/top_level.txt
pytility-0.3.0.dist-info/RECORD
