Metadata-Version: 2.1
Name: pytility
Version: 0.3.0
Summary: A lean collection of Python utilities
Home-page: https://gitlab.com/mshepherd/pytility
Author: Markus Shepherd
Author-email: markus.r.shepherd@gmail.com
License: MIT
Project-URL: Documentation, https://gitlab.com/mshepherd/pytility/blob/master/README.md
Project-URL: Source, https://gitlab.com/mshepherd/pytility
Project-URL: Tracker, https://gitlab.com/mshepherd/pytility/issues
Keywords: utility,utilities,pytility
Platform: UNKNOWN
Classifier: License :: OSI Approved :: MIT License
Classifier: Programming Language :: Python
Classifier: Programming Language :: Python :: 3.6
Classifier: Programming Language :: Python :: 3.7
Classifier: Programming Language :: Python :: 3.8
Classifier: Programming Language :: Python :: 3.9
Requires-Python: >=3.6.0
Provides-Extra: dates
Requires-Dist: python-dateutil ; extra == 'dates'
